{
  "vlink": "https://haoqicat-1253322599.costj.myqcloud.com/antd",
  "name": "用 Nextjs 开发 haoduoshipin.com",
  "price": "20",
  "intro": "使用阿里的蚂蚁设计来制作一套后台系统，玩转第三方组件库",
  "writing_to_who": "已经会 React 的，想要快速上手 Antd 的朋友",
  "learning_goal": "Antd 基本套路，文档导读，各种 React 常用工具的配合",
  "service": [
    "拿到所有视频和文字稿",
    "可以获取所有示例代码"
  ],
  "content": [
    {
      "header": "第一章 基础",
      "section": [
        {
          "title": "为何要选择 Nextjs ？",
          "link": "why"
        },
        {
          "title": "跑一个 Hello world",
          "link": "hello"
        },
        {
          "title": "添加路由",
          "link": "router"
        },
        {
          "title": "密码验证和跳转",
          "link": "redirect"
        },
        {
          "title": "配置文件",
          "link": "setting"
        }
      ]
    },
    {
      "header": "第二章 操作盘",
      "section": [
        {
          "title": "布局",
          "link": "dash-layout"
        },
        {
          "title": "登出",
          "link": "logout"
        },
        {
          "title": "受保护页面",
          "link": "protected"
        },
        {
          "title": "导航栏",
          "link": "navbar"
        },
        {
          "title": "导航栏刷新高亮",
          "link": "navbar-selected"
        },
        {
          "title": "表格 Table",
          "link": "table"
        },
        {
          "title": "json-sever 模拟 API",
          "link": "json"
        },
        {
          "title": "删除",
          "link": "delete"
        },
        {
          "title": "表单 form",
          "link": "form"
        },
        {
          "title": "控制 sidebar 高亮",
          "link": "selected"
        },
        {
          "title": "处理订单",
          "link": "orders"
        }
      ]
    },
    {
      "header": "第三章 收尾",
      "section": [
        {
          "title": "创建用户系统",
          "link": "user"
        },
        {
          "title": "结语",
          "link": "end"
        }
      ]
    }
  ]
}
